[
  {
    "name": "CABARET VOLTAIRE’S FINAL UK TOUR",
    "matchedTitle": "Cabaret Voltaire (band)",
    "wikipedia": true,
    "wikipediaUrl": "https://en.wikipedia.org/wiki/Cabaret_Voltaire_(band)",
    "popularityScore": 20,
    "tier": "D",
    "confidence": 0,
    "status": "uncertain",
    "source": "search",
    "sourceEventTitle": "CABARET VOLTAIRE’S FINAL UK TOUR",
    "lastUpdated": "2026-06-09T14:02:24.410Z"
  },
  {
    "name": "CABARET BINGO",
    "matchedTitle": "Linda Gerard",
    "wikipedia": true,
    "wikipediaUrl": "https://en.wikipedia.org/wiki/Linda_Gerard",
    "popularityScore": 15,
    "tier": "D",
    "confidence": 0,
    "status": "uncertain",
    "source": "search",
    "sourceEventTitle": "CABARET BINGO",
    "lastUpdated": "2026-06-05T14:19:20.338Z"
  },
  {
    "name": "A QUEER ICONS CABARET",
    "matchedTitle": "Cabaret (1972 film)",
    "wikipedia": true,
    "wikipediaUrl": "https://en.wikipedia.org/wiki/Cabaret_(1972_film)",
    "popularityScore": 20,
    "tier": "D",
    "confidence": 0,
    "status": "uncertain",
    "source": "search",
    "sourceEventTitle": "A QUEER ICONS CABARET",
    "lastUpdated": "2026-06-06T15:39:54.145Z"
  },
  {
    "name": "GALIFREY CABARET",
    "matchedTitle": null,
    "wikipedia": false,
    "wikipediaUrl": null,
    "popularityScore": 10,
    "tier": "D",
    "confidence": 0,
    "status": "failed",
    "source": null,
    "sourceEventTitle": "GALIFREY CABARET",
    "lastUpdated": "2026-06-09T14:31:32.962Z"
  },
  {
    "name": "MISCAST CABARET",
    "matchedTitle": "Eddie Redmayne",
    "wikipedia": true,
    "wikipediaUrl": "https://en.wikipedia.org/wiki/Eddie_Redmayne",
    "popularityScore": 23,
    "tier": "D",
    "confidence": 0,
    "status": "uncertain",
    "source": "search",
    "sourceEventTitle": "MISCAST CABARET",
    "lastUpdated": "2026-06-09T14:32:10.157Z"
  },
  {
    "name": "THE ROCK & ROLL MAGIC SHOW",
    "matchedTitle": "The Rolling Stones Rock and Roll Circus",
    "wikipedia": true,
    "wikipediaUrl": "https://en.wikipedia.org/wiki/The_Rolling_Stones_Rock_and_Roll_Circus",
    "popularityScore": 20,
    "tier": "D",
    "confidence": 0,
    "status": "uncertain",
    "source": "search",
    "sourceEventTitle": "THE ROCK & ROLL MAGIC SHOW",
    "lastUpdated": "2026-06-09T14:34:14.277Z"
  },
  {
    "name": "The Magic Of Motown",
    "matchedTitle": "Motown Magic",
    "wikipedia": true,
    "wikipediaUrl": "https://en.wikipedia.org/wiki/Motown_Magic",
    "popularityScore": 26,
    "tier": "D",
    "confidence": 0,
    "status": "uncertain",
    "source": "search",
    "sourceEventTitle": "The Magic Of Motown",
    "lastUpdated": "2026-06-08T09:10:57.863Z"
  },
  {
    "name": "Entertainers. Book",
    "matchedTitle": "Cedric the Entertainer",
    "wikipedia": true,
    "wikipediaUrl": "https://en.wikipedia.org/wiki/Cedric_the_Entertainer",
    "popularityScore": 20,
    "tier": "D",
    "confidence": 0,
    "status": "uncertain",
    "source": "search",
    "sourceEventTitle": "Man In The Mirror - A Tribute To Michael Jackson",
    "lastUpdated": "2026-06-09T14:02:33.856Z"
  },
  {
    "name": "The Illegal Eagles",
    "matchedTitle": "Child (band)",
    "wikipedia": true,
    "wikipediaUrl": "https://en.wikipedia.org/wiki/Child_(band)",
    "popularityScore": 20,
    "tier": "D",
    "confidence": 0,
    "status": "uncertain",
    "source": "search",
    "sourceEventTitle": "The Illegal Eagles",
    "lastUpdated": "2026-06-09T14:03:23.093Z"
  },
  {
    "name": "Luther UK",
    "matchedTitle": "List of Luther episodes",
    "wikipedia": true,
    "wikipediaUrl": "https://en.wikipedia.org/wiki/List_of_Luther_episodes",
    "popularityScore": 26,
    "tier": "D",
    "confidence": 0,
    "status": "uncertain",
    "source": "search",
    "sourceEventTitle": "Luther UK",
    "lastUpdated": "2026-06-09T14:04:02.478Z"
  },
  {
    "name": "Harry  Cambridge",
    "matchedTitle": "Harry Potter",
    "wikipedia": true,
    "wikipediaUrl": "https://en.wikipedia.org/wiki/Harry_Potter",
    "popularityScore": 20,
    "tier": "D",
    "confidence": 0,
    "status": "uncertain",
    "source": "search",
    "sourceEventTitle": "Luther UK",
    "lastUpdated": "2026-06-09T14:04:09.182Z"
  },
  {
    "name": "'My First Concert'",
    "matchedTitle": "My World Tour",
    "wikipedia": true,
    "wikipediaUrl": "https://en.wikipedia.org/wiki/My_World_Tour",
    "popularityScore": 23,
    "tier": "D",
    "confidence": 0,
    "status": "uncertain",
    "source": "search",
    "sourceEventTitle": "'My First Concert' Featuring Baby Shark, Pinkfong & The Zoomies",
    "lastUpdated": "2026-06-09T14:06:09.291Z"
  },
  {
    "name": "Johns' Boys Choir",
    "matchedTitle": "Boys Choir of Harlem",
    "wikipedia": true,
    "wikipediaUrl": "https://en.wikipedia.org/wiki/Boys_Choir_of_Harlem",
    "popularityScore": 20,
    "tier": "D",
    "confidence": 0,
    "status": "uncertain",
    "source": "search",
    "sourceEventTitle": "Johns' Boys Choir",
    "lastUpdated": "2026-06-09T14:06:16.396Z"
  },
  {
    "name": "Johns’ Boys",
    "matchedTitle": "John Boys",
    "wikipedia": true,
    "wikipediaUrl": "https://en.wikipedia.org/wiki/John_Boys",
    "popularityScore": 10,
    "tier": "D",
    "confidence": 0,
    "status": "uncertain",
    "source": "search",
    "sourceEventTitle": "Johns' Boys Choir",
    "lastUpdated": "2026-06-09T14:07:23.831Z"
  },
  {
    "name": "Fun For Little Ones",
    "matchedTitle": "Fun, Fun, Fun",
    "wikipedia": true,
    "wikipediaUrl": "https://en.wikipedia.org/wiki/Fun%2C_Fun%2C_Fun",
    "popularityScore": 20,
    "tier": "D",
    "confidence": 0,
    "status": "uncertain",
    "source": "search",
    "sourceEventTitle": "Fun For Little Ones - A Tribute To Ms Rachel",
    "lastUpdated": "2026-06-09T14:07:31.182Z"
  },
  {
    "name": "Piff & Pop's Magic Shoppe",
    "matchedTitle": null,
    "wikipedia": false,
    "wikipediaUrl": null,
    "popularityScore": 10,
    "tier": "D",
    "confidence": 0,
    "status": "failed",
    "source": null,
    "sourceEventTitle": "Piff & Pop's Magic Shoppe",
    "lastUpdated": "2026-06-09T14:08:13.586Z"
  },
  {
    "name": "Hannah East",
    "matchedTitle": "John Hannah (actor)",
    "wikipedia": true,
    "wikipediaUrl": "https://en.wikipedia.org/wiki/John_Hannah_(actor)",
    "popularityScore": 20,
    "tier": "D",
    "confidence": 0,
    "status": "uncertain",
    "source": "search",
    "sourceEventTitle": "Hannah East: Express Yourself",
    "lastUpdated": "2026-06-09T14:09:27.821Z"
  },
  {
    "name": "Michael Starring Ben",
    "matchedTitle": "Michael Jackson impersonator",
    "wikipedia": true,
    "wikipediaUrl": "https://en.wikipedia.org/wiki/Michael_Jackson_impersonator",
    "popularityScore": 20,
    "tier": "D",
    "confidence": 0,
    "status": "uncertain",
    "source": "search",
    "sourceEventTitle": "Michael Starring Ben",
    "lastUpdated": "2026-06-09T14:10:20.595Z"
  },
  {
    "name": "Hey Jude! Get Back With The Beatles",
    "matchedTitle": "Hey Jude (Beatles album)",
    "wikipedia": true,
    "wikipediaUrl": "https://en.wikipedia.org/wiki/Hey_Jude_(Beatles_album)",
    "popularityScore": 20,
    "tier": "D",
    "confidence": 0,
    "status": "uncertain",
    "source": "search",
    "sourceEventTitle": "Hey Jude! Get Back With The Beatles",
    "lastUpdated": "2026-06-09T14:10:29.906Z"
  },
  {
    "name": "The Beatles. Yesterday. Today.",
    "matchedTitle": "Yesterday and Today",
    "wikipedia": true,
    "wikipediaUrl": "https://en.wikipedia.org/wiki/Yesterday_and_Today",
    "popularityScore": 20,
    "tier": "D",
    "confidence": 0,
    "status": "uncertain",
    "source": "search",
    "sourceEventTitle": "Hey Jude! Get Back With The Beatles",
    "lastUpdated": "2026-06-09T14:11:09.647Z"
  },
  {
    "name": "Murder, She Didn't Write",
    "matchedTitle": "List of Murder, She Wrote episodes",
    "wikipedia": true,
    "wikipediaUrl": "https://en.wikipedia.org/wiki/List_of_Murder%2C_She_Wrote_episodes",
    "popularityScore": 20,
    "tier": "D",
    "confidence": 0,
    "status": "uncertain",
    "source": "search",
    "sourceEventTitle": "Murder, She Didn't Write",
    "lastUpdated": "2026-06-09T14:11:15.919Z"
  },
  {
    "name": "Michael Roulston",
    "matchedTitle": "Gutenberg! The Musical!",
    "wikipedia": true,
    "wikipediaUrl": "https://en.wikipedia.org/wiki/Gutenberg!_The_Musical!",
    "popularityScore": 20,
    "tier": "D",
    "confidence": 0,
    "status": "uncertain",
    "source": "search",
    "sourceEventTitle": "Fascinating Aïda",
    "lastUpdated": "2026-06-09T14:12:38.970Z"
  },
  {
    "name": "The Eternal Shame Of Sue Perkins",
    "matchedTitle": "Bull Moose Party",
    "wikipedia": true,
    "wikipediaUrl": "https://en.wikipedia.org/wiki/Bull_Moose_Party",
    "popularityScore": 20,
    "tier": "D",
    "confidence": 0,
    "status": "uncertain",
    "source": "search",
    "sourceEventTitle": "The Eternal Shame Of Sue Perkins",
    "lastUpdated": "2026-06-09T14:13:17.026Z"
  },
  {
    "name": "Siren Talent. Book",
    "matchedTitle": "Xanadu (musical)",
    "wikipedia": true,
    "wikipediaUrl": "https://en.wikipedia.org/wiki/Xanadu_(musical)",
    "popularityScore": 20,
    "tier": "D",
    "confidence": 0,
    "status": "uncertain",
    "source": "search",
    "sourceEventTitle": "Jon Culshaw: Me, Myself & Others",
    "lastUpdated": "2026-06-09T14:13:31.462Z"
  },
  {
    "name": "Steve Steinman's Fuel Injected Magic! 50th Anniversary Concert",
    "matchedTitle": null,
    "wikipedia": false,
    "wikipediaUrl": null,
    "popularityScore": 10,
    "tier": "D",
    "confidence": 0,
    "status": "failed",
    "source": null,
    "sourceEventTitle": "Steve Steinman's Fuel Injected Magic! 50th Anniversary Concert",
    "lastUpdated": "2026-06-09T14:15:23.899Z"
  },
  {
    "name": "Beefy’s Big Weekender: Jason Manford",
    "matchedTitle": null,
    "wikipedia": false,
    "wikipediaUrl": null,
    "popularityScore": 10,
    "tier": "D",
    "confidence": 0,
    "status": "failed",
    "source": null,
    "sourceEventTitle": "Beefy’s Big Weekender: Jason Manford",
    "lastUpdated": "2026-06-09T13:59:16.775Z"
  },
  {
    "name": "Beefy’s Big Weekender: Sara Pascoe",
    "matchedTitle": null,
    "wikipedia": false,
    "wikipediaUrl": null,
    "popularityScore": 10,
    "tier": "D",
    "confidence": 0,
    "status": "failed",
    "source": null,
    "sourceEventTitle": "Beefy’s Big Weekender: Sara Pascoe",
    "lastUpdated": "2026-06-09T14:00:27.851Z"
  },
  {
    "name": "Beefy’s Comedy Club: Guz Khan",
    "matchedTitle": null,
    "wikipedia": false,
    "wikipediaUrl": null,
    "popularityScore": 10,
    "tier": "D",
    "confidence": 0,
    "status": "failed",
    "source": null,
    "sourceEventTitle": "Beefy’s Comedy Club: Guz Khan",
    "lastUpdated": "2026-06-09T14:01:08.276Z"
  },
  {
    "name": "DINOSAURS, A STORY OF SURVIVAL / IMMERSIVE CINEMA",
    "matchedTitle": "Walking with Dinosaurs",
    "wikipedia": true,
    "wikipediaUrl": "https://en.wikipedia.org/wiki/Walking_with_Dinosaurs",
    "popularityScore": 20,
    "tier": "D",
    "confidence": 0,
    "status": "uncertain",
    "source": "search",
    "sourceEventTitle": "DINOSAURS, A STORY OF SURVIVAL / IMMERSIVE CINEMA",
    "lastUpdated": "2026-06-09T14:16:15.783Z"
  },
  {
    "name": "Daniel Foxx",
    "matchedTitle": "Jimmie Foxx",
    "wikipedia": true,
    "wikipediaUrl": "https://en.wikipedia.org/wiki/Jimmie_Foxx",
    "popularityScore": 20,
    "tier": "D",
    "confidence": 0,
    "status": "uncertain",
    "source": "search",
    "sourceEventTitle": "Daniel Foxx: How Lovely",
    "lastUpdated": "2026-06-08T09:23:10.734Z"
  },
  {
    "name": "DRAGWYL",
    "matchedTitle": null,
    "wikipedia": false,
    "wikipediaUrl": null,
    "popularityScore": 10,
    "tier": "D",
    "confidence": 0,
    "status": "failed",
    "source": null,
    "sourceEventTitle": "DRAGWYL",
    "lastUpdated": "2026-06-09T14:23:08.259Z"
  },
  {
    "name": "GAGGED JUNE",
    "matchedTitle": "Albert Lee",
    "wikipedia": true,
    "wikipediaUrl": "https://en.wikipedia.org/wiki/Albert_Lee",
    "popularityScore": 23,
    "tier": "D",
    "confidence": 0,
    "status": "uncertain",
    "source": "search",
    "sourceEventTitle": "GAGGED JUNE",
    "lastUpdated": "2026-06-09T14:24:23.138Z"
  },
  {
    "name": "STEPH WEBBER",
    "matchedTitle": "Steph McGovern",
    "wikipedia": true,
    "wikipediaUrl": "https://en.wikipedia.org/wiki/Steph_McGovern",
    "popularityScore": 29,
    "tier": "D",
    "confidence": 0,
    "status": "uncertain",
    "source": "search",
    "sourceEventTitle": "STEPH WEBBER - GLITTERING NIGHTS",
    "lastUpdated": "2026-06-09T14:28:01.596Z"
  },
  {
    "name": "QUARTEY & BLAYNEY",
    "matchedTitle": "List of people with given name Peter",
    "wikipedia": true,
    "wikipediaUrl": "https://en.wikipedia.org/wiki/List_of_people_with_given_name_Peter",
    "popularityScore": 20,
    "tier": "D",
    "confidence": 0,
    "status": "uncertain",
    "source": "search",
    "sourceEventTitle": "QUARTEY & BLAYNEY",
    "lastUpdated": "2026-06-09T14:29:32.042Z"
  },
  {
    "name": "Carwyn Blayney",
    "matchedTitle": "So You Think You're Funny",
    "wikipedia": true,
    "wikipediaUrl": "https://en.wikipedia.org/wiki/So_You_Think_You're_Funny",
    "popularityScore": 20,
    "tier": "D",
    "confidence": 0,
    "status": "uncertain",
    "source": "search",
    "sourceEventTitle": "QUARTEY & BLAYNEY",
    "lastUpdated": "2026-06-09T14:30:08.196Z"
  },
  {
    "name": "MICHAEL AKADIRI",
    "matchedTitle": "Aïssa Maïga",
    "wikipedia": true,
    "wikipediaUrl": "https://en.wikipedia.org/wiki/A%C3%AFssa_Ma%C3%AFga",
    "popularityScore": 20,
    "tier": "D",
    "confidence": 0,
    "status": "uncertain",
    "source": "search",
    "sourceEventTitle": "MICHAEL AKADIRI: DON’T CALL ME UNCLE!",
    "lastUpdated": "2026-06-09T12:04:24.685Z"
  },
  {
    "name": "SOUNDS OF THE OCEAN / IMMERSIVE CINEMA",
    "matchedTitle": "U2:UV Achtung Baby Live at Sphere",
    "wikipedia": true,
    "wikipediaUrl": "https://en.wikipedia.org/wiki/U2%3AUV_Achtung_Baby_Live_at_Sphere",
    "popularityScore": 20,
    "tier": "D",
    "confidence": 0,
    "status": "uncertain",
    "source": "search",
    "sourceEventTitle": "SOUNDS OF THE OCEAN / IMMERSIVE CINEMA",
    "lastUpdated": "2026-06-09T14:16:23.624Z"
  },
  {
    "name": "Inception This Land",
    "matchedTitle": "History of life",
    "wikipedia": true,
    "wikipediaUrl": "https://en.wikipedia.org/wiki/History_of_life",
    "popularityScore": 20,
    "tier": "D",
    "confidence": 0,
    "status": "uncertain",
    "source": "search",
    "sourceEventTitle": "Candlelight: Hans Zimmer's Best Works",
    "lastUpdated": "2026-06-09T14:17:35.306Z"
  },
  {
    "name": "The Lion King Zooster’s",
    "matchedTitle": "List of Madagascar (franchise) characters",
    "wikipedia": true,
    "wikipediaUrl": "https://en.wikipedia.org/wiki/List_of_Madagascar_(franchise)_characters",
    "popularityScore": 20,
    "tier": "D",
    "confidence": 0,
    "status": "uncertain",
    "source": "search",
    "sourceEventTitle": "Candlelight: Hans Zimmer's Best Works",
    "lastUpdated": "2026-06-09T14:17:46.163Z"
  },
  {
    "name": "Madagascar Supermarine",
    "matchedTitle": "Israeli Air Force Museum",
    "wikipedia": true,
    "wikipediaUrl": "https://en.wikipedia.org/wiki/Israeli_Air_Force_Museum",
    "popularityScore": 20,
    "tier": "D",
    "confidence": 0,
    "status": "uncertain",
    "source": "search",
    "sourceEventTitle": "Candlelight: Hans Zimmer's Best Works",
    "lastUpdated": "2026-06-09T14:18:03.341Z"
  },
  {
    "name": "Dunkirk Honor",
    "matchedTitle": "Dunkirk, New York",
    "wikipedia": true,
    "wikipediaUrl": "https://en.wikipedia.org/wiki/Dunkirk%2C_New_York",
    "popularityScore": 20,
    "tier": "D",
    "confidence": 0,
    "status": "uncertain",
    "source": "search",
    "sourceEventTitle": "Candlelight: Hans Zimmer's Best Works",
    "lastUpdated": "2026-06-09T14:18:09.210Z"
  },
  {
    "name": "The Dark Knight Wonder",
    "matchedTitle": "The Dark Knight Strikes Again",
    "wikipedia": true,
    "wikipediaUrl": "https://en.wikipedia.org/wiki/The_Dark_Knight_Strikes_Again",
    "popularityScore": 20,
    "tier": "D",
    "confidence": 0,
    "status": "uncertain",
    "source": "search",
    "sourceEventTitle": "Candlelight: Hans Zimmer's Best Works",
    "lastUpdated": "2026-06-09T14:19:18.595Z"
  },
  {
    "name": "Interstellar Dune Suite Gladiator",
    "matchedTitle": "The Last Samurai (soundtrack)",
    "wikipedia": true,
    "wikipediaUrl": "https://en.wikipedia.org/wiki/The_Last_Samurai_(soundtrack)",
    "popularityScore": 23,
    "tier": "D",
    "confidence": 0,
    "status": "uncertain",
    "source": "search",
    "sourceEventTitle": "Candlelight: Hans Zimmer's Best Works",
    "lastUpdated": "2026-06-09T14:19:27.880Z"
  },
  {
    "name": "Sherlock Holmes Pirates",
    "matchedTitle": "Sherlock Holmes pastiches",
    "wikipedia": true,
    "wikipediaUrl": "https://en.wikipedia.org/wiki/Sherlock_Holmes_pastiches",
    "popularityScore": 20,
    "tier": "D",
    "confidence": 0,
    "status": "uncertain",
    "source": "search",
    "sourceEventTitle": "Candlelight: Hans Zimmer's Best Works",
    "lastUpdated": "2026-06-09T14:19:34.581Z"
  },
  {
    "name": "Hayao Miyazaki's Dreams by Mystery Ensemble",
    "matchedTitle": "Castle in the Sky",
    "wikipedia": true,
    "wikipediaUrl": "https://en.wikipedia.org/wiki/Castle_in_the_Sky",
    "popularityScore": 20,
    "tier": "D",
    "confidence": 0,
    "status": "uncertain",
    "source": "search",
    "sourceEventTitle": "Hayao Miyazaki's Dreams by Mystery Ensemble",
    "lastUpdated": "2026-06-09T14:20:12.157Z"
  },
  {
    "name": "Seriously Collins",
    "matchedTitle": "...But Seriously",
    "wikipedia": true,
    "wikipediaUrl": "https://en.wikipedia.org/wiki/...But_Seriously",
    "popularityScore": 20,
    "tier": "D",
    "confidence": 0,
    "status": "uncertain",
    "source": "search",
    "sourceEventTitle": "Seriously Collins - The Candlelight Concert",
    "lastUpdated": "2026-06-09T14:20:19.115Z"
  },
  {
    "name": "WAITRESS",
    "matchedTitle": "Waiting staff",
    "wikipedia": true,
    "wikipediaUrl": "https://en.wikipedia.org/wiki/Waiting_staff",
    "popularityScore": 20,
    "tier": "D",
    "confidence": 0,
    "status": "uncertain",
    "source": "search",
    "sourceEventTitle": "WAITRESS",
    "lastUpdated": "2026-06-09T14:21:26.212Z"
  },
  {
    "name": "CONSTANTINOPOLIAD",
    "matchedTitle": "82nd Venice International Film Festival",
    "wikipedia": true,
    "wikipediaUrl": "https://en.wikipedia.org/wiki/82nd_Venice_International_Film_Festival",
    "popularityScore": 20,
    "tier": "D",
    "confidence": 0,
    "status": "uncertain",
    "source": "search",
    "sourceEventTitle": "CONSTANTINOPOLIAD",
    "lastUpdated": "2026-06-09T14:21:44.694Z"
  },
  {
    "name": "THE SCHITTS SHOW",
    "matchedTitle": "Schitt's Creek",
    "wikipedia": true,
    "wikipediaUrl": "https://en.wikipedia.org/wiki/Schitt's_Creek",
    "popularityScore": 23,
    "tier": "D",
    "confidence": 0,
    "status": "uncertain",
    "source": "search",
    "sourceEventTitle": "THE SCHITTS SHOW",
    "lastUpdated": "2026-06-09T14:23:14.743Z"
  },
  {
    "name": "Danny Bayne",
    "matchedTitle": "Grease (musical)",
    "wikipedia": true,
    "wikipediaUrl": "https://en.wikipedia.org/wiki/Grease_(musical)",
    "popularityScore": 20,
    "tier": "D",
    "confidence": 0,
    "status": "uncertain",
    "source": "search",
    "sourceEventTitle": "FAWLTY TOWERS THE PLAY",
    "lastUpdated": "2026-06-09T14:25:09.673Z"
  },
  {
    "name": "UNITY FESTIVAL’S GRAND OPENING",
    "matchedTitle": "2024 Summer Olympics opening ceremony",
    "wikipedia": true,
    "wikipediaUrl": "https://en.wikipedia.org/wiki/2024_Summer_Olympics_opening_ceremony",
    "popularityScore": 20,
    "tier": "D",
    "confidence": 0,
    "status": "uncertain",
    "source": "search",
    "sourceEventTitle": "UNITY FESTIVAL’S GRAND OPENING",
    "lastUpdated": "2026-06-09T14:25:20.146Z"
  },
  {
    "name": "Danza Mobile",
    "matchedTitle": "National Dance Academy (Italy)",
    "wikipedia": true,
    "wikipediaUrl": "https://en.wikipedia.org/wiki/National_Dance_Academy_(Italy)",
    "popularityScore": 15,
    "tier": "D",
    "confidence": 0,
    "status": "uncertain",
    "source": "search",
    "sourceEventTitle": "UNITY FESTIVAL’S GRAND OPENING",
    "lastUpdated": "2026-06-09T14:26:27.119Z"
  },
  {
    "name": "Fou Fou Kaboom",
    "matchedTitle": "List of LGBTQ-related films of 2010",
    "wikipedia": true,
    "wikipediaUrl": "https://en.wikipedia.org/wiki/List_of_LGBTQ-related_films_of_2010",
    "popularityScore": 20,
    "tier": "D",
    "confidence": 0,
    "status": "uncertain",
    "source": "search",
    "sourceEventTitle": "THE PEARL REVUE",
    "lastUpdated": "2026-06-09T14:26:40.959Z"
  },
  {
    "name": "BIG BAND BURLESQUE",
    "matchedTitle": "Minsky's Burlesque",
    "wikipedia": true,
    "wikipediaUrl": "https://en.wikipedia.org/wiki/Minsky's_Burlesque",
    "popularityScore": 20,
    "tier": "D",
    "confidence": 0,
    "status": "uncertain",
    "source": "search",
    "sourceEventTitle": "BIG BAND BURLESQUE",
    "lastUpdated": "2026-06-09T14:27:17.278Z"
  },
  {
    "name": "Pete Saunders.\n\nLeading",
    "matchedTitle": "Ryan Saunders",
    "wikipedia": true,
    "wikipediaUrl": "https://en.wikipedia.org/wiki/Ryan_Saunders",
    "popularityScore": 20,
    "tier": "D",
    "confidence": 0,
    "status": "uncertain",
    "source": "search",
    "sourceEventTitle": "BIG BAND BURLESQUE",
    "lastUpdated": "2026-06-09T14:27:24.415Z"
  },
  {
    "name": "SHOWGIRLS AND SHARKS",
    "matchedTitle": "Elizabeth Berkley",
    "wikipedia": true,
    "wikipediaUrl": "https://en.wikipedia.org/wiki/Elizabeth_Berkley",
    "popularityScore": 23,
    "tier": "D",
    "confidence": 0,
    "status": "uncertain",
    "source": "search",
    "sourceEventTitle": "SHOWGIRLS AND SHARKS",
    "lastUpdated": "2026-06-09T14:28:11.070Z"
  },
  {
    "name": "THE RAT PACK LAS VEGAS LIVE!",
    "matchedTitle": "The Rat Pack: Live from Las Vegas",
    "wikipedia": true,
    "wikipediaUrl": "https://en.wikipedia.org/wiki/The_Rat_Pack%3A_Live_from_Las_Vegas",
    "popularityScore": 15,
    "tier": "D",
    "confidence": 0,
    "status": "uncertain",
    "source": "search",
    "sourceEventTitle": "THE RAT PACK LAS VEGAS LIVE!",
    "lastUpdated": "2026-06-09T14:28:18.049Z"
  },
  {
    "name": "Magician Arron Jones",
    "matchedTitle": "Owain Glyndŵr",
    "wikipedia": true,
    "wikipediaUrl": "https://en.wikipedia.org/wiki/Owain_Glynd%C5%B5r",
    "popularityScore": 20,
    "tier": "D",
    "confidence": 0,
    "status": "uncertain",
    "source": "search",
    "sourceEventTitle": "THE ROCK & ROLL MAGIC SHOW",
    "lastUpdated": "2026-06-09T12:06:31.839Z"
  },
  {
    "name": "MIDGITTE BARDOT'S PERSONAL SPOT",
    "matchedTitle": null,
    "wikipedia": false,
    "wikipediaUrl": null,
    "popularityScore": 10,
    "tier": "D",
    "confidence": 0,
    "status": "failed",
    "source": null,
    "sourceEventTitle": "MIDGITTE BARDOT'S PERSONAL SPOT",
    "lastUpdated": "2026-06-09T14:32:20.058Z"
  },
  {
    "name": "Wilderness Festival",
    "matchedTitle": "Cornbury Park",
    "wikipedia": true,
    "wikipediaUrl": "https://en.wikipedia.org/wiki/Cornbury_Park",
    "popularityScore": 15,
    "tier": "D",
    "confidence": 0,
    "status": "uncertain",
    "source": "search",
    "sourceEventTitle": "MIDGITTE BARDOT'S PERSONAL SPOT",
    "lastUpdated": "2026-06-09T14:33:28.914Z"
  },
  {
    "name": "LEROY BRITO",
    "matchedTitle": "Episode 1 (Baby Reindeer)",
    "wikipedia": true,
    "wikipediaUrl": "https://en.wikipedia.org/wiki/Episode_1_(Baby_Reindeer)",
    "popularityScore": 20,
    "tier": "D",
    "confidence": 0,
    "status": "uncertain",
    "source": "search",
    "sourceEventTitle": "LEROY BRITO - HALFTIME",
    "lastUpdated": "2026-06-09T14:34:20.569Z"
  },
  {
    "name": "Tom Davis",
    "matchedTitle": "Thomas Davis",
    "wikipedia": true,
    "wikipediaUrl": "https://en.wikipedia.org/wiki/Thomas_Davis",
    "popularityScore": 10,
    "tier": "D",
    "confidence": 5,
    "status": "uncertain",
    "source": "direct",
    "sourceEventTitle": "Tom Davis: Spudgun",
    "lastUpdated": "2026-06-09T14:09:42.013Z"
  },
  {
    "name": "Self Esteem",
    "matchedTitle": "Self-esteem",
    "wikipedia": true,
    "wikipediaUrl": "https://en.wikipedia.org/wiki/Self-esteem",
    "popularityScore": 10,
    "tier": "D",
    "confidence": 5,
    "status": "uncertain",
    "source": "direct",
    "sourceEventTitle": "Self Esteem",
    "lastUpdated": "2026-06-09T13:58:00.196Z"
  },
  {
    "name": "The Pacific",
    "matchedTitle": "Pacific Ocean",
    "wikipedia": true,
    "wikipediaUrl": "https://en.wikipedia.org/wiki/Pacific_Ocean",
    "popularityScore": 10,
    "tier": "D",
    "confidence": 5,
    "status": "uncertain",
    "source": "direct",
    "sourceEventTitle": "Candlelight: Hans Zimmer's Best Works",
    "lastUpdated": "2026-06-09T14:18:12.063Z"
  },
  {
    "name": "Rebecca Lucy Taylor",
    "matchedTitle": "Self Esteem (musician)",
    "wikipedia": true,
    "wikipediaUrl": "https://en.wikipedia.org/wiki/Self_Esteem_(musician)",
    "popularityScore": 10,
    "tier": "D",
    "confidence": 10,
    "status": "uncertain",
    "source": "direct",
    "sourceEventTitle": "Self Esteem",
    "lastUpdated": "2026-06-09T13:58:05.263Z"
  },
  {
    "name": "CABARET PROVOCATEUR",
    "matchedTitle": "Bridget Everett",
    "wikipedia": true,
    "wikipediaUrl": "https://en.wikipedia.org/wiki/Bridget_Everett",
    "popularityScore": 20,
    "tier": "D",
    "confidence": 20,
    "status": "uncertain",
    "source": "search",
    "sourceEventTitle": "CABARET PROVOCATEUR",
    "lastUpdated": "2026-05-30T15:18:43.700Z"
  },
  {
    "name": "THE PEARL REVUE",
    "matchedTitle": "The Hollywood Revue",
    "wikipedia": true,
    "wikipediaUrl": "https://en.wikipedia.org/wiki/The_Hollywood_Revue",
    "popularityScore": 20,
    "tier": "D",
    "confidence": 20,
    "status": "uncertain",
    "source": "search",
    "sourceEventTitle": "THE PEARL REVUE",
    "lastUpdated": "2026-06-09T14:26:34.877Z"
  },
  {
    "name": "MRS DOUBTFIRE",
    "matchedTitle": "Mrs. Doubtfire",
    "wikipedia": true,
    "wikipediaUrl": "https://en.wikipedia.org/wiki/Mrs._Doubtfire",
    "popularityScore": 20,
    "tier": "D",
    "confidence": 20,
    "status": "uncertain",
    "source": "search",
    "sourceEventTitle": "MRS DOUBTFIRE",
    "lastUpdated": "2026-06-07T15:55:15.408Z"
  },
  {
    "name": "FAWLTY TOWERS THE PLAY",
    "matchedTitle": "Fawlty Towers: The Play",
    "wikipedia": true,
    "wikipediaUrl": "https://en.wikipedia.org/wiki/Fawlty_Towers%3A_The_Play",
    "popularityScore": 18,
    "tier": "D",
    "confidence": 20,
    "status": "uncertain",
    "source": "search",
    "sourceEventTitle": "FAWLTY TOWERS THE PLAY",
    "lastUpdated": "2026-06-09T14:24:29.812Z"
  },
  {
    "name": "THE ALTERNATIVE CABARET",
    "matchedTitle": "Alternative Cabaret",
    "wikipedia": true,
    "wikipediaUrl": "https://en.wikipedia.org/wiki/Alternative_Cabaret",
    "popularityScore": 15,
    "tier": "D",
    "confidence": 30,
    "status": "uncertain",
    "source": "search",
    "sourceEventTitle": "THE ALTERNATIVE CABARET: MUSICALS",
    "lastUpdated": "2026-06-09T14:33:36.099Z"
  },
  {
    "name": "Keith Brymer Jones and Marj Hogarth",
    "matchedTitle": "Keith Brymer Jones",
    "wikipedia": true,
    "wikipediaUrl": "https://en.wikipedia.org/wiki/Keith_Brymer_Jones",
    "popularityScore": 20,
    "tier": "D",
    "confidence": 30,
    "status": "uncertain",
    "source": "search",
    "sourceEventTitle": "Keith Brymer Jones and Marj Hogarth: Us, Pots and A Welsh Chapel",
    "lastUpdated": "2026-06-09T14:03:10.947Z"
  },
  {
    "name": "Princess Proms",
    "matchedTitle": "Prom",
    "wikipedia": true,
    "wikipediaUrl": "https://en.wikipedia.org/wiki/Prom",
    "popularityScore": 20,
    "tier": "D",
    "confidence": 30,
    "status": "uncertain",
    "source": "search",
    "sourceEventTitle": "Princess Proms",
    "lastUpdated": "2026-06-09T14:05:23.290Z"
  },
  {
    "name": "London’s Adelphi Theatre.",
    "matchedTitle": "Adelphi Theatre",
    "wikipedia": true,
    "wikipediaUrl": "https://en.wikipedia.org/wiki/Adelphi_Theatre",
    "popularityScore": 20,
    "tier": "D",
    "confidence": 30,
    "status": "uncertain",
    "source": "search",
    "sourceEventTitle": "Sweet Caroline - A Tribute To Neil Diamond",
    "lastUpdated": "2026-06-09T14:05:32.068Z"
  },
  {
    "name": "The Pub Landlord.\nAlso",
    "matchedTitle": "Landlord",
    "wikipedia": true,
    "wikipediaUrl": "https://en.wikipedia.org/wiki/Landlord",
    "popularityScore": 20,
    "tier": "D",
    "confidence": 30,
    "status": "uncertain",
    "source": "search",
    "sourceEventTitle": "Al Murray - All You Need Is Guv",
    "lastUpdated": "2026-06-09T14:09:36.949Z"
  },
  {
    "name": "Sky Full Of Stars",
    "matchedTitle": "A Sky Full of Stars",
    "wikipedia": true,
    "wikipediaUrl": "https://en.wikipedia.org/wiki/A_Sky_Full_of_Stars",
    "popularityScore": 20,
    "tier": "D",
    "confidence": 30,
    "status": "uncertain",
    "source": "search",
    "sourceEventTitle": "Sky Full Of Stars",
    "lastUpdated": "2026-06-09T14:11:24.874Z"
  },
  {
    "name": "Sky Full",
    "matchedTitle": "A Sky Full of Stars",
    "wikipedia": true,
    "wikipediaUrl": "https://en.wikipedia.org/wiki/A_Sky_Full_of_Stars",
    "popularityScore": 20,
    "tier": "D",
    "confidence": 30,
    "status": "uncertain",
    "source": "search",
    "sourceEventTitle": "Sky Full Of Stars",
    "lastUpdated": "2026-06-09T14:12:32.349Z"
  },
  {
    "name": "BBC's Amandaland",
    "matchedTitle": "Amandaland",
    "wikipedia": true,
    "wikipediaUrl": "https://en.wikipedia.org/wiki/Amandaland",
    "popularityScore": 23,
    "tier": "D",
    "confidence": 30,
    "status": "uncertain",
    "source": "search",
    "sourceEventTitle": "QUARTEY & BLAYNEY",
    "lastUpdated": "2026-06-09T14:30:14.840Z"
  },
  {
    "name": "GAGGED OCTOBER",
    "matchedTitle": "Gag",
    "wikipedia": true,
    "wikipediaUrl": "https://en.wikipedia.org/wiki/Gag",
    "popularityScore": 15,
    "tier": "D",
    "confidence": 30,
    "status": "uncertain",
    "source": "search",
    "sourceEventTitle": "GAGGED OCTOBER",
    "lastUpdated": "2026-06-03T15:38:15.240Z"
  },
  {
    "name": "JIVE ACES",
    "matchedTitle": "The Jive Aces",
    "wikipedia": true,
    "wikipediaUrl": "https://en.wikipedia.org/wiki/The_Jive_Aces",
    "popularityScore": 20,
    "tier": "D",
    "confidence": 30,
    "status": "uncertain",
    "source": "search",
    "sourceEventTitle": "JIVE ACES",
    "lastUpdated": "2026-06-09T14:30:21.868Z"
  },
  {
    "name": "GINGER JOHNSON",
    "matchedTitle": "Ginger Johnson (drag queen)",
    "wikipedia": true,
    "wikipediaUrl": "https://en.wikipedia.org/wiki/Ginger_Johnson_(drag_queen)",
    "popularityScore": 20,
    "tier": "D",
    "confidence": 30,
    "status": "uncertain",
    "source": "search",
    "sourceEventTitle": "GINGER JOHNSON - SHOW PONY",
    "lastUpdated": "2026-06-09T12:03:02.680Z"
  },
  {
    "name": "Beefy's Comedy Club. Sunday",
    "matchedTitle": "The Socially Distant Sports Bar",
    "wikipedia": true,
    "wikipediaUrl": "https://en.wikipedia.org/wiki/The_Socially_Distant_Sports_Bar",
    "popularityScore": 20,
    "tier": "D",
    "confidence": 35,
    "status": "uncertain",
    "source": "search",
    "sourceEventTitle": "Beefy’s Comedy Club: Guz Khan",
    "lastUpdated": "2026-06-09T14:01:14.552Z"
  },
  {
    "name": "The Wizard",
    "matchedTitle": "Wizard",
    "wikipedia": true,
    "wikipediaUrl": "https://en.wikipedia.org/wiki/Wizard",
    "popularityScore": 15,
    "tier": "D",
    "confidence": 40,
    "status": "uncertain",
    "source": "direct",
    "sourceEventTitle": "Rick Wakeman - The Wizard Of Prog",
    "lastUpdated": "2026-06-09T14:13:24.620Z"
  },
  {
    "name": "John van der Put",
    "matchedTitle": "Piff the Magic Dragon",
    "wikipedia": true,
    "wikipediaUrl": "https://en.wikipedia.org/wiki/Piff_the_Magic_Dragon",
    "popularityScore": 26,
    "tier": "D",
    "confidence": 45,
    "status": "uncertain",
    "source": "direct",
    "sourceEventTitle": "Piff & Pop's Magic Shoppe",
    "lastUpdated": "2026-06-09T14:08:18.654Z"
  },
  {
    "name": "The Pub Landlord",
    "matchedTitle": "Al Murray",
    "wikipedia": true,
    "wikipediaUrl": "https://en.wikipedia.org/wiki/Al_Murray",
    "popularityScore": 15,
    "tier": "D",
    "confidence": 45,
    "status": "uncertain",
    "source": "direct",
    "sourceEventTitle": "Al Murray - All You Need Is Guv",
    "lastUpdated": "2026-06-09T14:09:39.482Z"
  },
  {
    "name": "Li Jin Hao",
    "matchedTitle": "Jin Hao Li",
    "wikipedia": true,
    "wikipediaUrl": "https://en.wikipedia.org/wiki/Jin_Hao_Li",
    "popularityScore": 41,
    "tier": "C",
    "confidence": 45,
    "status": "uncertain",
    "source": "search",
    "sourceEventTitle": "Li Jin Hao: Falling from a Moon",
    "lastUpdated": "2026-06-09T14:15:39.061Z"
  },
  {
    "name": "Count Arthur Strong",
    "matchedTitle": "Steve Delaney",
    "wikipedia": true,
    "wikipediaUrl": "https://en.wikipedia.org/wiki/Steve_Delaney",
    "popularityScore": 24,
    "tier": "D",
    "confidence": 50,
    "status": "uncertain",
    "source": "direct",
    "sourceEventTitle": "Count Arthur Strong - And It's Goodnight From Me!",
    "lastUpdated": "2026-06-09T14:14:06.664Z"
  },
  {
    "name": "SOOZ KEMPNER",
    "matchedTitle": "Sooz Kempner",
    "wikipedia": true,
    "wikipediaUrl": "https://en.wikipedia.org/wiki/Sooz_Kempner",
    "popularityScore": 40,
    "tier": "C",
    "confidence": 50,
    "status": "uncertain",
    "source": "search",
    "sourceEventTitle": "SOOZ KEMPNER: IMPOSTER",
    "lastUpdated": "2026-06-07T11:07:08.884Z"
  },
  {
    "name": "WELSH NATIONAL OPERA",
    "matchedTitle": "Welsh National Opera",
    "wikipedia": true,
    "wikipediaUrl": "https://en.wikipedia.org/wiki/Welsh_National_Opera",
    "popularityScore": 40,
    "tier": "C",
    "confidence": 50,
    "status": "uncertain",
    "source": "search",
    "sourceEventTitle": "WELSH NATIONAL OPERA: THE ANONYMOUS LOVER",
    "lastUpdated": "2026-06-09T12:07:15.673Z"
  },
  {
    "name": "GIANT STEPS",
    "matchedTitle": "Giant Steps",
    "wikipedia": true,
    "wikipediaUrl": "https://en.wikipedia.org/wiki/Giant_Steps",
    "popularityScore": 40,
    "tier": "C",
    "confidence": 50,
    "status": "uncertain",
    "source": "search",
    "sourceEventTitle": "GIANT STEPS",
    "lastUpdated": "2026-06-08T13:29:20.990Z"
  },
  {
    "name": "DIANA ROSS",
    "matchedTitle": "Diana Ross",
    "wikipedia": true,
    "wikipediaUrl": "https://en.wikipedia.org/wiki/Diana_Ross",
    "popularityScore": 40,
    "tier": "C",
    "confidence": 50,
    "status": "uncertain",
    "source": "search",
    "sourceEventTitle": "DIANA ROSS - TAMEKA JACKSON",
    "lastUpdated": "2026-06-09T14:22:21.973Z"
  },
  {
    "name": "DISNEY PRINCESS",
    "matchedTitle": "Disney Princess",
    "wikipedia": true,
    "wikipediaUrl": "https://en.wikipedia.org/wiki/Disney_Princess",
    "popularityScore": 40,
    "tier": "C",
    "confidence": 50,
    "status": "uncertain",
    "source": "search",
    "sourceEventTitle": "DISNEY PRINCESS - THE CONCERT",
    "lastUpdated": "2026-06-09T14:34:29.194Z"
  },
  {
    "name": "CHRISTOPHER HALL",
    "matchedTitle": "Christopher Hall",
    "wikipedia": true,
    "wikipediaUrl": "https://en.wikipedia.org/wiki/Christopher_Hall",
    "popularityScore": 25,
    "tier": "D",
    "confidence": 50,
    "status": "uncertain",
    "source": "search",
    "sourceEventTitle": "CHRISTOPHER HALL - PIZAZZ",
    "lastUpdated": "2026-06-09T12:06:38.971Z"
  },
  {
    "name": "Ed Byrne",
    "matchedTitle": "Edward Byrne",
    "wikipedia": true,
    "wikipediaUrl": "https://en.wikipedia.org/wiki/Edward_Byrne",
    "popularityScore": 25,
    "tier": "D",
    "confidence": 50,
    "status": "uncertain",
    "source": "direct",
    "sourceEventTitle": "Ed Byrne - No Dramas",
    "lastUpdated": "2026-06-09T14:14:14.312Z"
  },
  {
    "name": "BACK TO THE FUTURE",
    "matchedTitle": "Back to the Future",
    "wikipedia": true,
    "wikipediaUrl": "https://en.wikipedia.org/wiki/Back_to_the_Future",
    "popularityScore": 40,
    "tier": "C",
    "confidence": 50,
    "status": "uncertain",
    "source": "search",
    "sourceEventTitle": "BACK TO THE FUTURE",
    "lastUpdated": "2026-06-09T14:35:10.555Z"
  },
  {
    "name": "Baby Reindeer'",
    "matchedTitle": "Baby Reindeer",
    "wikipedia": true,
    "wikipediaUrl": "https://en.wikipedia.org/wiki/Baby_Reindeer",
    "popularityScore": 43,
    "tier": "C",
    "confidence": 55,
    "status": "uncertain",
    "source": "search",
    "sourceEventTitle": "Mark Watson: Before It Overtakes Us",
    "lastUpdated": "2026-06-09T14:15:30.247Z"
  },
  {
    "name": "JUDITH OWEN",
    "matchedTitle": "Judith Owen",
    "wikipedia": true,
    "wikipediaUrl": "https://en.wikipedia.org/wiki/Judith_Owen",
    "popularityScore": 40,
    "tier": "C",
    "confidence": 55,
    "status": "uncertain",
    "source": "search",
    "sourceEventTitle": "JUDITH OWEN",
    "lastUpdated": "2026-06-04T14:03:17.719Z"
  },
  {
    "name": "ANDREW BIRD",
    "matchedTitle": "Andrew Bird",
    "wikipedia": true,
    "wikipediaUrl": "https://en.wikipedia.org/wiki/Andrew_Bird",
    "popularityScore": 40,
    "tier": "C",
    "confidence": 55,
    "status": "uncertain",
    "source": "search",
    "sourceEventTitle": "ANDREW BIRD - ON THE EDGE TOUR",
    "lastUpdated": "2026-06-07T22:07:21.088Z"
  },
  {
    "name": "The Enormous Crocodile",
    "matchedTitle": "The Enormous Crocodile",
    "wikipedia": true,
    "wikipediaUrl": "https://en.wikipedia.org/wiki/The_Enormous_Crocodile",
    "popularityScore": 35,
    "tier": "D",
    "confidence": 60,
    "status": "uncertain",
    "source": "direct",
    "sourceEventTitle": "The Enormous Crocodile",
    "lastUpdated": "2026-05-30T10:25:20.407Z"
  },
  {
    "name": "Man In The Mirror",
    "matchedTitle": "Man in the Mirror",
    "wikipedia": true,
    "wikipediaUrl": "https://en.wikipedia.org/wiki/Man_in_the_Mirror",
    "popularityScore": 30,
    "tier": "D",
    "confidence": 60,
    "status": "uncertain",
    "source": "direct",
    "sourceEventTitle": "Man In The Mirror - A Tribute To Michael Jackson",
    "lastUpdated": "2026-06-09T14:02:26.940Z"
  },
  {
    "name": "Lost In Music",
    "matchedTitle": "Lost in Music",
    "wikipedia": true,
    "wikipediaUrl": "https://en.wikipedia.org/wiki/Lost_in_Music",
    "popularityScore": 35,
    "tier": "D",
    "confidence": 60,
    "status": "uncertain",
    "source": "direct",
    "sourceEventTitle": "Lost In Music",
    "lastUpdated": "2026-06-09T14:03:13.480Z"
  },
  {
    "name": "Never Too Much",
    "matchedTitle": "Never Too Much",
    "wikipedia": true,
    "wikipediaUrl": "https://en.wikipedia.org/wiki/Never_Too_Much",
    "popularityScore": 33,
    "tier": "D",
    "confidence": 60,
    "status": "uncertain",
    "source": "direct",
    "sourceEventTitle": "Luther UK",
    "lastUpdated": "2026-06-09T14:04:11.717Z"
  },
  {
    "name": "Sweet Caroline",
    "matchedTitle": "Sweet Caroline",
    "wikipedia": true,
    "wikipediaUrl": "https://en.wikipedia.org/wiki/Sweet_Caroline",
    "popularityScore": 35,
    "tier": "D",
    "confidence": 60,
    "status": "uncertain",
    "source": "direct",
    "sourceEventTitle": "Sweet Caroline - A Tribute To Neil Diamond",
    "lastUpdated": "2026-06-09T14:05:25.822Z"
  },
  {
    "name": "Sam Campbell",
    "matchedTitle": "Samuel Campbell",
    "wikipedia": true,
    "wikipediaUrl": "https://en.wikipedia.org/wiki/Samuel_Campbell",
    "popularityScore": 43,
    "tier": "C",
    "confidence": 60,
    "status": "uncertain",
    "source": "direct",
    "sourceEventTitle": "Sam Campbell: Kid Giblet",
    "lastUpdated": "2026-06-09T14:07:33.714Z"
  },
  {
    "name": "Magic Dragon",
    "matchedTitle": "Magic Dragon",
    "wikipedia": true,
    "wikipediaUrl": "https://en.wikipedia.org/wiki/Magic_Dragon",
    "popularityScore": 30,
    "tier": "D",
    "confidence": 60,
    "status": "uncertain",
    "source": "direct",
    "sourceEventTitle": "Piff & Pop's Magic Shoppe",
    "lastUpdated": "2026-06-09T14:08:16.122Z"
  },
  {
    "name": "Serena Terry",
    "matchedTitle": "Serena Terry",
    "wikipedia": true,
    "wikipediaUrl": "https://en.wikipedia.org/wiki/Serena_Terry",
    "popularityScore": 30,
    "tier": "D",
    "confidence": 60,
    "status": "uncertain",
    "source": "direct",
    "sourceEventTitle": "Serena Terry: Therapy",
    "lastUpdated": "2026-06-09T14:09:30.353Z"
  },
  {
    "name": "Step Into Christmas",
    "matchedTitle": "Step into Christmas",
    "wikipedia": true,
    "wikipediaUrl": "https://en.wikipedia.org/wiki/Step_into_Christmas",
    "popularityScore": 35,
    "tier": "D",
    "confidence": 60,
    "status": "uncertain",
    "source": "direct",
    "sourceEventTitle": "Step Into Christmas",
    "lastUpdated": "2026-06-09T14:10:23.129Z"
  },
  {
    "name": "The Beatles",
    "matchedTitle": "The Beatles",
    "wikipedia": true,
    "wikipediaUrl": "https://en.wikipedia.org/wiki/The_Beatles",
    "popularityScore": 35,
    "tier": "D",
    "confidence": 60,
    "status": "uncertain",
    "source": "direct",
    "sourceEventTitle": "Hey Jude! Get Back With The Beatles",
    "lastUpdated": "2026-06-09T14:10:32.430Z"
  },
  {
    "name": "Radio Gaga",
    "matchedTitle": "Radio Gaga",
    "wikipedia": true,
    "wikipediaUrl": "https://en.wikipedia.org/wiki/Radio_Gaga",
    "popularityScore": 33,
    "tier": "D",
    "confidence": 60,
    "status": "uncertain",
    "source": "direct",
    "sourceEventTitle": "Radio Gaga",
    "lastUpdated": "2026-06-09T14:11:18.449Z"
  },
  {
    "name": "Scott Bennett",
    "matchedTitle": "Scott Bennett",
    "wikipedia": true,
    "wikipediaUrl": "https://en.wikipedia.org/wiki/Scott_Bennett",
    "popularityScore": 35,
    "tier": "D",
    "confidence": 60,
    "status": "uncertain",
    "source": "direct",
    "sourceEventTitle": "Scott Bennett: Stuff",
    "lastUpdated": "2026-06-09T14:13:19.557Z"
  },
  {
    "name": "Rick Wakeman",
    "matchedTitle": "Rick Wakeman",
    "wikipedia": true,
    "wikipediaUrl": "https://en.wikipedia.org/wiki/Rick_Wakeman",
    "popularityScore": 35,
    "tier": "D",
    "confidence": 60,
    "status": "uncertain",
    "source": "direct",
    "sourceEventTitle": "Rick Wakeman - The Wizard Of Prog",
    "lastUpdated": "2026-06-09T14:13:22.088Z"
  },
  {
    "name": "Troy Hawke",
    "matchedTitle": "Milo McCabe",
    "wikipedia": true,
    "wikipediaUrl": "https://en.wikipedia.org/wiki/Milo_McCabe",
    "popularityScore": 36,
    "tier": "D",
    "confidence": 60,
    "status": "uncertain",
    "source": "direct",
    "sourceEventTitle": "Troy Hawke: Never Stop, Never Change!",
    "lastUpdated": "2026-06-09T14:13:33.993Z"
  },
  {
    "name": "The Silence Of The Lambs",
    "matchedTitle": "The Silence of the Lambs",
    "wikipedia": true,
    "wikipediaUrl": "https://en.wikipedia.org/wiki/The_Silence_of_the_Lambs",
    "popularityScore": 38,
    "tier": "D",
    "confidence": 60,
    "status": "uncertain",
    "source": "direct",
    "sourceEventTitle": "The Silence Of The Lambs",
    "lastUpdated": "2026-06-09T14:14:09.251Z"
  },
  {
    "name": "David Gray",
    "matchedTitle": "David Gray",
    "wikipedia": true,
    "wikipediaUrl": "https://en.wikipedia.org/wiki/David_Gray",
    "popularityScore": 30,
    "tier": "D",
    "confidence": 60,
    "status": "uncertain",
    "source": "direct",
    "sourceEventTitle": "David Gray – Past & Present Tour",
    "lastUpdated": "2026-06-09T13:57:57.604Z"
  },
  {
    "name": "Prioritise Pleasure",
    "matchedTitle": "Prioritise Pleasure",
    "wikipedia": true,
    "wikipediaUrl": "https://en.wikipedia.org/wiki/Prioritise_Pleasure",
    "popularityScore": 35,
    "tier": "D",
    "confidence": 60,
    "status": "uncertain",
    "source": "direct",
    "sourceEventTitle": "Self Esteem",
    "lastUpdated": "2026-06-09T13:58:02.731Z"
  },
  {
    "name": "James B Partridge",
    "matchedTitle": "James B Partridge",
    "wikipedia": true,
    "wikipediaUrl": "https://en.wikipedia.org/wiki/James_B_Partridge",
    "popularityScore": 35,
    "tier": "D",
    "confidence": 60,
    "status": "uncertain",
    "source": "direct",
    "sourceEventTitle": "James B Partridge presents The Big Christmas Assembly",
    "lastUpdated": "2026-06-09T14:01:17.083Z"
  },
  {
    "name": "Amber Davies",
    "matchedTitle": "Amber Davies",
    "wikipedia": true,
    "wikipediaUrl": "https://en.wikipedia.org/wiki/Amber_Davies",
    "popularityScore": 33,
    "tier": "D",
    "confidence": 60,
    "status": "uncertain",
    "source": "direct",
    "sourceEventTitle": "LEGALLY BLONDE",
    "lastUpdated": "2026-06-09T14:22:24.507Z"
  },
  {
    "name": "DOG MAN",
    "matchedTitle": "Dog Man",
    "wikipedia": true,
    "wikipediaUrl": "https://en.wikipedia.org/wiki/Dog_Man",
    "popularityScore": 35,
    "tier": "D",
    "confidence": 60,
    "status": "uncertain",
    "source": "direct",
    "sourceEventTitle": "DOG MAN: THE MUSICAL",
    "lastUpdated": "2026-06-09T12:04:27.203Z"
  },
  {
    "name": "Candlelight",
    "matchedTitle": "Candlelight",
    "wikipedia": true,
    "wikipediaUrl": "https://en.wikipedia.org/wiki/Candlelight",
    "popularityScore": 35,
    "tier": "D",
    "confidence": 60,
    "status": "uncertain",
    "source": "direct",
    "sourceEventTitle": "Candlelight: Tribute to Fleetwood Mac",
    "lastUpdated": "2026-06-09T14:16:26.205Z"
  },
  {
    "name": "The Times",
    "matchedTitle": "The Times",
    "wikipedia": true,
    "wikipediaUrl": "https://en.wikipedia.org/wiki/The_Times",
    "popularityScore": 35,
    "tier": "D",
    "confidence": 60,
    "status": "uncertain",
    "source": "direct",
    "sourceEventTitle": "WAITRESS",
    "lastUpdated": "2026-06-09T14:21:31.276Z"
  },
  {
    "name": "The Stage",
    "matchedTitle": "The Stage",
    "wikipedia": true,
    "wikipediaUrl": "https://en.wikipedia.org/wiki/The_Stage",
    "popularityScore": 35,
    "tier": "D",
    "confidence": 60,
    "status": "uncertain",
    "source": "direct",
    "sourceEventTitle": "WAITRESS",
    "lastUpdated": "2026-06-09T14:21:33.811Z"
  },
  {
    "name": "Time Out",
    "matchedTitle": "Time out",
    "wikipedia": true,
    "wikipediaUrl": "https://en.wikipedia.org/wiki/Time_out",
    "popularityScore": 30,
    "tier": "D",
    "confidence": 60,
    "status": "uncertain",
    "source": "direct",
    "sourceEventTitle": "WAITRESS",
    "lastUpdated": "2026-06-09T14:21:36.344Z"
  },
  {
    "name": "It Girl",
    "matchedTitle": "It girl",
    "wikipedia": true,
    "wikipediaUrl": "https://en.wikipedia.org/wiki/It_girl",
    "popularityScore": 30,
    "tier": "D",
    "confidence": 60,
    "status": "uncertain",
    "source": "direct",
    "sourceEventTitle": "LEGALLY BLONDE",
    "lastUpdated": "2026-06-09T14:22:27.038Z"
  },
  {
    "name": "Radio Times",
    "matchedTitle": "Radio Times",
    "wikipedia": true,
    "wikipediaUrl": "https://en.wikipedia.org/wiki/Radio_Times",
    "popularityScore": 41,
    "tier": "C",
    "confidence": 60,
    "status": "uncertain",
    "source": "direct",
    "sourceEventTitle": "FAWLTY TOWERS THE PLAY",
    "lastUpdated": "2026-06-09T14:24:32.345Z"
  },
  {
    "name": "The Voice UK",
    "matchedTitle": "The Voice UK",
    "wikipedia": true,
    "wikipediaUrl": "https://en.wikipedia.org/wiki/The_Voice_UK",
    "popularityScore": 46,
    "tier": "C",
    "confidence": 60,
    "status": "uncertain",
    "source": "direct",
    "sourceEventTitle": "STEPH WEBBER - GLITTERING NIGHTS",
    "lastUpdated": "2026-06-09T14:28:04.129Z"
  },
  {
    "name": "Jim Whitley",
    "matchedTitle": "Jim Whitley",
    "wikipedia": true,
    "wikipediaUrl": "https://en.wikipedia.org/wiki/Jim_Whitley",
    "popularityScore": 30,
    "tier": "D",
    "confidence": 60,
    "status": "uncertain",
    "source": "direct",
    "sourceEventTitle": "THE RAT PACK LAS VEGAS LIVE!",
    "lastUpdated": "2026-06-09T14:29:20.791Z"
  },
  {
    "name": "BBC Breakfast",
    "matchedTitle": "BBC Breakfast",
    "wikipedia": true,
    "wikipediaUrl": "https://en.wikipedia.org/wiki/BBC_Breakfast",
    "popularityScore": 41,
    "tier": "C",
    "confidence": 60,
    "status": "uncertain",
    "source": "direct",
    "sourceEventTitle": "AN EVENING WITH SIR DAVID JASON",
    "lastUpdated": "2026-06-09T14:29:23.389Z"
  },
  {
    "name": "West End",
    "matchedTitle": "West End",
    "wikipedia": true,
    "wikipediaUrl": "https://en.wikipedia.org/wiki/West_End",
    "popularityScore": 30,
    "tier": "D",
    "confidence": 60,
    "status": "uncertain",
    "source": "direct",
    "sourceEventTitle": "DISNEY PRINCESS - THE CONCERT",
    "lastUpdated": "2026-06-09T14:34:31.725Z"
  },
  {
    "name": "Donna Summer",
    "matchedTitle": "Donna Summer",
    "wikipedia": true,
    "wikipediaUrl": "https://en.wikipedia.org/wiki/Donna_Summer",
    "popularityScore": 30,
    "tier": "D",
    "confidence": 65,
    "status": "uncertain",
    "source": "direct",
    "sourceEventTitle": "Lost In Music",
    "lastUpdated": "2026-06-09T14:03:16.004Z"
  },
  {
    "name": "Shoot From The Hip",
    "matchedTitle": "Shoot from the Hip",
    "wikipedia": true,
    "wikipediaUrl": "https://en.wikipedia.org/wiki/Shoot_from_the_Hip",
    "popularityScore": 35,
    "tier": "D",
    "confidence": 65,
    "status": "uncertain",
    "source": "direct",
    "sourceEventTitle": "Shoot From The Hip",
    "lastUpdated": "2026-06-09T14:03:25.627Z"
  },
  {
    "name": "In The Air Tonight",
    "matchedTitle": "In the Air Tonight",
    "wikipedia": true,
    "wikipediaUrl": "https://en.wikipedia.org/wiki/In_the_Air_Tonight",
    "popularityScore": 35,
    "tier": "D",
    "confidence": 65,
    "status": "uncertain",
    "source": "direct",
    "sourceEventTitle": "In The Air Tonight",
    "lastUpdated": "2026-06-09T14:04:14.261Z"
  },
  {
    "name": "John Barrowman",
    "matchedTitle": "John Barrowman",
    "wikipedia": true,
    "wikipediaUrl": "https://en.wikipedia.org/wiki/John_Barrowman",
    "popularityScore": 35,
    "tier": "D",
    "confidence": 65,
    "status": "uncertain",
    "source": "direct",
    "sourceEventTitle": "John Barrowman: My Life In Musicals",
    "lastUpdated": "2026-06-09T14:08:21.184Z"
  },
  {
    "name": "John Partridge",
    "matchedTitle": "John Partridge",
    "wikipedia": true,
    "wikipediaUrl": "https://en.wikipedia.org/wiki/John_Partridge",
    "popularityScore": 35,
    "tier": "D",
    "confidence": 65,
    "status": "uncertain",
    "source": "direct",
    "sourceEventTitle": "The Silence Of The Lambs",
    "lastUpdated": "2026-06-09T14:14:11.781Z"
  },
  {
    "name": "Alfie Boe",
    "matchedTitle": "Alfie Boe",
    "wikipedia": true,
    "wikipediaUrl": "https://en.wikipedia.org/wiki/Alfie_Boe",
    "popularityScore": 30,
    "tier": "D",
    "confidence": 65,
    "status": "uncertain",
    "source": "direct",
    "sourceEventTitle": "Alfie Boe",
    "lastUpdated": "2026-05-31T21:38:06.479Z"
  },
  {
    "name": "Dav Pilkey",
    "matchedTitle": "Dav Pilkey",
    "wikipedia": true,
    "wikipediaUrl": "https://en.wikipedia.org/wiki/Dav_Pilkey",
    "popularityScore": 35,
    "tier": "D",
    "confidence": 65,
    "status": "uncertain",
    "source": "direct",
    "sourceEventTitle": "DOG MAN: THE MUSICAL",
    "lastUpdated": "2026-06-09T12:04:29.709Z"
  },
  {
    "name": "Jessie Nelson",
    "matchedTitle": "Jessie Nelson",
    "wikipedia": true,
    "wikipediaUrl": "https://en.wikipedia.org/wiki/Jessie_Nelson",
    "popularityScore": 30,
    "tier": "D",
    "confidence": 65,
    "status": "uncertain",
    "source": "direct",
    "sourceEventTitle": "WAITRESS",
    "lastUpdated": "2026-06-09T14:21:28.744Z"
  },
  {
    "name": "Joanne Clifton",
    "matchedTitle": "Joanne Clifton",
    "wikipedia": true,
    "wikipediaUrl": "https://en.wikipedia.org/wiki/Joanne_Clifton",
    "popularityScore": 38,
    "tier": "D",
    "confidence": 65,
    "status": "uncertain",
    "source": "direct",
    "sourceEventTitle": "FAWLTY TOWERS THE PLAY",
    "lastUpdated": "2026-06-09T14:25:12.206Z"
  }
]